LICENSE.txt
MANIFEST.in
README.txt
query_comments.sql
query_tickets.sql
setup.py
tratihubis.py
test/cutplace_comments.csv
test/cutplace_tickets.csv
test/test_comments.csv
test/test_tickets.csv
test/test_tratihubis.py
tratihubis.egg-info/PKG-INFO
tratihubis.egg-info/SOURCES.txt
tratihubis.egg-info/dependency_links.txt
tratihubis.egg-info/entry_points.txt
tratihubis.egg-info/requires.txt
tratihubis.egg-info/top_level.txt