Metadata-Version: 1.1
Name: tratihubis
Version: 0.3
Summary: convert Trac tickets to Github issues
Home-page: http://pypi.python.org/pypi/tratihubis/
Author: Thomas Aglassinger
Author-email: roskakori@users.sourceforge.net
License: BSD License
Keywords: trac github ticket issue convert migrate
Platform: UNKNOWN
Classifier: Development Status :: 3 - Alpha
Classifier: Environment :: Console
Classifier: Intended Audience :: Developers
Classifier: License :: OSI Approved :: BSD License
Classifier: Natural Language :: English
Classifier: Operating System :: OS Independent
Classifier: Programming Language :: Python :: 2.6
Classifier: Programming Language :: Python :: 2.7
Classifier: Topic :: Software Development :: Bug Tracking
